.travis.yml
NOTICE.txt
README.rst
bootstrap.py
buildout.cfg
eke.biomarker.sublime-project
setup.cfg
setup.py
travis.cfg
docs/Classes and Relationships.graffle
docs/HISTORY.txt
docs/INSTALL.txt
docs/LICENSE.txt
eke/__init__.py
eke.biomarker.egg-info/PKG-INFO
eke.biomarker.egg-info/SOURCES.txt
eke.biomarker.egg-info/dependency_links.txt
eke.biomarker.egg-info/entry_points.txt
eke.biomarker.egg-info/namespace_packages.txt
eke.biomarker.egg-info/not-zip-safe
eke.biomarker.egg-info/requires.txt
eke.biomarker.egg-info/top_level.txt
eke/biomarker/README.rst
eke/biomarker/__init__.py
eke/biomarker/cancerdataexpo_client.py
eke/biomarker/config.py
eke/biomarker/configure.zcml
eke/biomarker/interfaces.py
eke/biomarker/testing.py
eke/biomarker/upgrades.py
eke/biomarker/upgrades.zcml
eke/biomarker/utils.py
eke/biomarker/browser/__init__.py
eke/biomarker/browser/configure.zcml
eke/biomarker/browser/edrn-biomarker.css
eke/biomarker/browser/rdf.py
eke/biomarker/browser/tabber-minimized.js
eke/biomarker/browser/views.py
eke/biomarker/browser/images/biomarker-body-system.gif
eke/biomarker/browser/images/biomarker-folder.gif
eke/biomarker/browser/images/biomarker-panel.gif
eke/biomarker/browser/images/biomarker_analytics_thumbnail.png
eke/biomarker/browser/images/body-system-study.gif
eke/biomarker/browser/images/cliaCert.png
eke/biomarker/browser/images/elemental-biomarker.gif
eke/biomarker/browser/images/fdaCert.png
eke/biomarker/browser/images/review-listing.gif
eke/biomarker/browser/images/study-bg.gif
eke/biomarker/browser/images/study-statistics.gif
eke/biomarker/browser/images/studyBottomLeft.gif
eke/biomarker/browser/images/studyBottomRight.gif
eke/biomarker/browser/images/studyTopLeft.gif
eke/biomarker/browser/images/studyTopRight.gif
eke/biomarker/browser/templates/biomarker_summary_report.pt
eke/biomarker/browser/templates/biomarkerbodysystem.pt
eke/biomarker/browser/templates/biomarkerfields.pt
eke/biomarker/browser/templates/biomarkerfolder.pt
eke/biomarker/browser/templates/biomarkerpanel.pt
eke/biomarker/browser/templates/bodysystemstudy.pt
eke/biomarker/browser/templates/elementalbiomarker.pt
eke/biomarker/browser/templates/phasingfields.pt
eke/biomarker/browser/templates/pis_by_biomarker.pt
eke/biomarker/browser/templates/qafields.pt
